pyramid/__init__.py
pyramid/constants.py
pyramid/dummy.py
pyramid/evaluator.py
pyramid/generator.py
pyramid/gpu_check.py
pyramid/importers.py
pyramid/pyramid.py
pyramid/trainer.py
pyramid/utils.py
pyramid/cache/__init__.py
pyramid/cache/read.py
pyramid/cache/tree.py
pyramid/cache/write.py
pyramid/data/__init__.py
pyramid/data/bounding_box.py
pyramid/data/dataset.py
pyramid/data/generate.py
pyramid/data/image.py
pyramid/data/numpy.py
pyramid/data/stratify.py
pyramid/data/tabular.py
pyramid/data/transform.py
pyramid/data/visualize.py
pyramid/serialize/__init__.py
pyramid/serialize/data.py
pyramid/serialize/extract.py
pyramid/serialize/serialize.py
pyramid/serialize/tree.py
pyramid/serialize/utils.py
pyramid/settings/__init__.py
pyramid/settings/base_settings.py
pyramid/settings/bounding_box_loss.py
pyramid/settings/image.py
pyramid/settings/job_settings.py
pyramid/settings/objectives.py
pyramid/settings/optimizers.py
pyramid/train/__init__.py
pyramid/train/callbacks.py
pyramid/train/finalize.py
pyramid/train/importances.py
pyramid/train/metrics.py
pyramid/train/model.py
bigml_pyramid-0.4.0.dist-info/METADATA
bigml_pyramid-0.4.0.dist-info/WHEEL
bigml_pyramid-0.4.0.dist-info/entry_points.txt
bigml_pyramid-0.4.0.dist-info/top_level.txt
bigml_pyramid-0.4.0.dist-info/RECORD
