Metadata-Version: 2.1
Name: bigml-pyramid
Version: 0.4.0
Summary: BigML wrapper for TensorFlow
Home-page: http://bigml.com/
Author: BigML Team
Author-email: team@bigml.com
Requires-Dist: bigml-sensenet <0.7.3,>=0.7.2
Requires-Dist: inputimeout <1.1,>=1.0.4
Requires-Dist: numpy <1.27,>=1.26.3
Requires-Dist: pillow <10.2.1,>=10.2.0
Requires-Dist: scikit-learn <1.4.1,>=1.4.0
Requires-Dist: scipy <1.13.0,>=1.12.0
Requires-Dist: shapsplain <0.3.1,>=0.3.0
Requires-Dist: tensorflow <2.16,>=2.15
